pyclusterprofiler/GO_utilities.py
pyclusterprofiler/KEGG_utilities.py
pyclusterprofiler/__init__.py
pyclusterprofiler/_version.py
pyclusterprofiler/clusters.py
pyclusterprofiler/plotting.py
pyclusterprofiler/utilities.py
pyclusterprofiler-0.1.dev14.dist-info/LICENSE.txt
pyclusterprofiler-0.1.dev14.dist-info/METADATA
pyclusterprofiler-0.1.dev14.dist-info/WHEEL
pyclusterprofiler-0.1.dev14.dist-info/top_level.txt
pyclusterprofiler-0.1.dev14.dist-info/RECORD
