Metadata-Version: 2.1
Name: pyclusterprofiler
Version: 0.1.dev14
Summary: Tools for analyzing pathway enrichment of gene lists
Home-page: https://github.com/lukebfunk/pyclusterprofiler
Author: Luke Funk
Author-email: lukefunk@broadinstitute.org
License: MIT
Platform: UNKNOWN
Classifier: Programming Language :: Python
Classifier: Programming Language :: Python :: 3
Classifier: Programming Language :: Python :: 3.6
Classifier: Programming Language :: Python :: 3.7
Classifier: Programming Language :: Python :: 3.8
Classifier: Programming Language :: Python :: Implementation :: CPython
Classifier: Programming Language :: Python :: Implementation :: PyPy
Classifier: Operating System :: OS Independent
Classifier: License :: OSI Approved :: MIT License
Requires-Python: >=3.6
Requires-Dist: sharepathway (==0.5.0)
Requires-Dist: goatools (==1.0.15)
Requires-Dist: statsmodels
Requires-Dist: scipy
Requires-Dist: seaborn
Requires-Dist: pandas
Requires-Dist: numpy
